granola/__init__.py
granola/_version.py
granola/breakfast_cereal.py
granola/command_readers.py
granola/enums.py
granola/main.py
granola/serial_sniffer.py
granola/utils.py
granola/hooks/__init__.py
granola/hooks/base_hook.py
granola/hooks/hooks.py
granola/tests/__init__.py
granola/tests/conftest.py
granola/tests/test_attribute_access.py
granola/tests/test_deprecations.py
granola/tests/test_enums.py
granola/tests/test_serial_cmd_obj.py
granola/tests/test_setup.py
granola/tests/test_utils.py
granola-0.9.3.dist-info/LICENSE.txt
granola-0.9.3.dist-info/METADATA
granola-0.9.3.dist-info/WHEEL
granola-0.9.3.dist-info/top_level.txt
granola-0.9.3.dist-info/RECORD
