Metadata-Version: 2.1
Name: granola
Version: 0.9.3
Summary: Generating Real-time Autonomous N-device Output without Linked Apparatuses
Home-page: https://granola.readthedocs.io/
Author: GRANOLA Development Team
Author-email: granola@metergroup.com
Project-URL: Bug Tracker, https://github.com/metergroup/GRANOLA/issues
Project-URL: Documentation, https://granola.readthedocs.io/
Project-URL: Source Code, https://github.com/metergroup/GRANOLA
Classifier: Programming Language :: Python :: 2.7
Classifier: Programming Language :: Python :: 3.5
Classifier: Programming Language :: Python :: 3.6
Classifier: Programming Language :: Python :: 3.7
Classifier: Programming Language :: Python :: 3.8
Classifier: Programming Language :: Python :: 3.9
Classifier: Programming Language :: Python :: 3.10
Classifier: Operating System :: OS Independent
Requires-Python: !=3.0.*,!=3.1.*,!=3.2.*,!=3.3*,!=3.4*,>=2.7
License-File: LICENSE.txt
Requires-Dist: pandas
Requires-Dist: pyserial (>=2.6)
Requires-Dist: future (>=0.18.2)
Requires-Dist: attrs (>=21)
Requires-Dist: more-itertools
Requires-Dist: Jinja2 (>=2.0)
Requires-Dist: mock ; python_version < "3"
Requires-Dist: pathlib (>=1.0.1) ; python_version < "3"
Requires-Dist: aenum (>=3) ; python_version <= "3.5"
Provides-Extra: dev
Requires-Dist: versioneer (==0.18) ; extra == 'dev'
Requires-Dist: pre-commit ; extra == 'dev'
Requires-Dist: flake8 ; extra == 'dev'
Requires-Dist: invoke ; extra == 'dev'
Requires-Dist: isort ; ((python_version > "3" and sys_platform == "win32") or sys_platform != "win32") and extra == 'dev'
Requires-Dist: lexicon ; (python_version < "3") and extra == 'dev'
Requires-Dist: black (<=21.12b0) ; (python_version > "3.6") and extra == 'dev'
Requires-Dist: black[jupyter] (<=21.12b0) ; (python_version > "3.6") and extra == 'dev'
Requires-Dist: click (<8.1.0) ; (python_version > "3.6") and extra == 'dev'
Provides-Extra: docs
Requires-Dist: myst-parser ; (python_version > "3") and extra == 'docs'
Requires-Dist: sphinx ; (python_version > "3") and extra == 'docs'
Requires-Dist: sphinx-rtd-theme ; (python_version > "3") and extra == 'docs'
Requires-Dist: ipython ; (python_version > "3") and extra == 'docs'
Requires-Dist: ipykernel ; (python_version > "3") and extra == 'docs'
Requires-Dist: myst-nb ; (python_version > "3") and extra == 'docs'
Provides-Extra: examples
Requires-Dist: ipython ; extra == 'examples'
Requires-Dist: ipykernel ; extra == 'examples'
Requires-Dist: jupyter ; (python_version > "3") and extra == 'examples'
Provides-Extra: test
Requires-Dist: pytest ; extra == 'test'
Requires-Dist: pytest-cov ; extra == 'test'
